{
  "_config": {
    "startStep": "reveil",
    "initialStats": {
      "oxy": 100,
      "sante": 100
    },
    "statLabels": {
      "oxy": "🫁 Oxygène",
      "sante": "❤️ Santé"
    }
  },
  "reveil": {
    "text": "Le froid vous tire d'un sommeil sans rêves, [NAME]. L'Icare-7 dérive, et chaque seconde, une partie de votre vie s'échappe par les micro-fissures de la coque. \n\nVous êtes [SEX] seul(e). Vos capteurs indiquent que les réserves d'air s'amenuisent.",
    "onEnter": { "oxy": -5 },
    "choices": [
      { "text": "Explorer la baie de stockage", "next": "baie_stockage" },
      { "text": "Aller directement au cockpit", "next": "cockpit" }
    ]
  },
  "baie_stockage": {
    "text": "Au milieu des débris, vous trouvez une 'Puce d'Accès'. Elle brille d'une lueur bleue rassurante.",
    "onEnter": { "oxy": -10, "getItem": "puce" },
    "choices": [
      { "text": "Retourner au couloir", "next": "reveil" }
    ]
  },
  "cockpit": {
    "text": "Le terminal principal clignote. Il demande une Puce d'Accès pour stabiliser l'orbite.",
    "onEnter": { "oxy": -5 },
    "choices": [
      { "text": "Insérer la Puce d'Accès", "next": "fin_victoire", "require": "puce" },
      { "text": "Tenter une manoeuvre manuelle (Désespéré)", "next": "mort_manoeuvre" }
    ]
  },
  "fin_victoire": {
    "text": "Les moteurs s'allument avec un grognement puissant. L'orbite est stabilisée. La Terre vous répond enfin. Vous avez réussi, commandant(e) [NAME] !",
    "choices": [ { "text": "Menu Principal", "next": "reveil" } ]
  },
  "mort_manoeuvre": {
    "text": "Sans aide informatique, vous poussez les moteurs trop fort. La navette se désintègre sous la pression. Votre voyage s'arrête ici.",
    "onEnter": { "sante": -100 },
    "choices": []
  }
}
